COPYRIGHT.txt
LICENSE.txt
MANIFEST.in
README.txt
setup.cfg
setup.py
version.py
docs/HISTORY.txt
docs/Makefile
docs/api.txt
docs/conf.py
docs/example.txt
docs/index.txt
gs/__init__.py
gs.config.egg-info/PKG-INFO
gs.config.egg-info/SOURCES.txt
gs.config.egg-info/dependency_links.txt
gs.config.egg-info/entry_points.txt
gs.config.egg-info/namespace_packages.txt
gs.config.egg-info/not-zip-safe
gs.config.egg-info/requires.txt
gs.config.egg-info/top_level.txt
gs/config/__init__.py
gs/config/config.py
gs/config/configure.zcml
gs/config/errors.py
gs/config/tests/__init__.py
gs/config/tests/config.py
gs/config/tests/test_all.py